pqwidgets/PQButton.py
pqwidgets/PQImage.py
pqwidgets/PQImageButton.py
pqwidgets/PQLabel.py
pqwidgets/__init__.py
pqwidgets-1.0.8.dist-info/METADATA
pqwidgets-1.0.8.dist-info/WHEEL
pqwidgets-1.0.8.dist-info/top_level.txt
pqwidgets-1.0.8.dist-info/RECORD
